FindAndReplace/__init__.py
FindAndReplace/FindAndReplace.py
FindAndReplace-0.1.1.dist-info/top_level.txt
FindAndReplace-0.1.1.dist-info/WHEEL
FindAndReplace-0.1.1.dist-info/DESCRIPTION.rst
FindAndReplace-0.1.1.dist-info/RECORD
FindAndReplace-0.1.1.dist-info/metadata.json
FindAndReplace-0.1.1.dist-info/pbr.json
FindAndReplace-0.1.1.dist-info/METADATA
FAR/__init__.py
FAR/FAR.py
