Metadata-Version: 2.0
Name: FindAndReplace
Version: 0.1.1
Summary: Find And Replace
Home-page: https://github.com/shantanu561993/FAR
Author: Shantanu Khandelwal
Author-email: shantanu561993@gmail.com
License: GPLv3+
Keywords: Find And Replace
Platform: UNKNOWN
Classifier: Development Status :: 2 - Pre-Alpha
Classifier: Intended Audience :: Developers
Classifier: License :: OSI Approved :: BSD License
Classifier: Natural Language :: English
Classifier: Programming Language :: Python :: 2
Classifier: Programming Language :: Python :: 2.6
Classifier: Programming Language :: Python :: 2.7
Classifier: Programming Language :: Python :: 3
Classifier: Programming Language :: Python :: 3.3
Classifier: Programming Language :: Python :: 3.4
